<?xml version="1.0" encoding="UTF-8"?>
<opml version="2.0">
  <head>
    <title>RSSForge - 订阅源</title>
    <ownerName>RSSForge</ownerName>
    <ownerEmail>noreply@gitfox-enter.github.io</ownerEmail>
    <dateCreated>2026-06-20</dateCreated>
  </head>
  <body>
    <outline type="rss" text="12345线报" title="12345线报" xmlUrl="https://gitfox-enter.github.io/RSSForge/feeds/12345%E7%BA%BF%E6%8A%A5.xml" />
    <outline type="rss" text="慢慢买" title="慢慢买" xmlUrl="https://gitfox-enter.github.io/RSSForge/feeds/%E6%85%A2%E6%85%A2%E4%B9%B0.xml" />
    <outline type="rss" text="果核剥壳" title="果核剥壳" xmlUrl="https://gitfox-enter.github.io/RSSForge/feeds/guo-he-bao-ke.xml" htmlUrl="https://www.ghxi.com/" iconUrl="https://gitfox-enter.github.io/RSSForge/public/icons/guo-he-bao-ke.png" />
    <outline type="rss" text="汇发部" title="汇发部" xmlUrl="https://gitfox-enter.github.io/RSSForge/feeds/hui-fa-bu.xml" htmlUrl="https://www.huifabu.cn/" iconUrl="https://gitfox-enter.github.io/RSSForge/public/icons/hui-fa-bu.png" />
    <outline type="rss" text="活动5" title="活动5" xmlUrl="https://gitfox-enter.github.io/RSSForge/feeds/%E6%B4%BB%E5%8A%A85.xml" />
    <outline type="rss" text="白菜哦" title="白菜哦" xmlUrl="https://gitfox-enter.github.io/RSSForge/feeds/%E7%99%BD%E8%8F%9C%E5%93%A6.xml" />
    <outline type="rss" text="网赚" title="网赚" xmlUrl="https://gitfox-enter.github.io/RSSForge/feeds/%E7%BD%91%E8%B5%9A.xml" />
  </body>
</opml>